AUTHORS
LICENSE
MANIFEST.in
README
setup.cfg
setup.py
django_notification_op.egg-info/PKG-INFO
django_notification_op.egg-info/SOURCES.txt
django_notification_op.egg-info/dependency_links.txt
django_notification_op.egg-info/not-zip-safe
django_notification_op.egg-info/top_level.txt
docs/index.txt
docs/usage.txt
notification/.___init__.py
notification/._atomformat.py
notification/._feeds.py
notification/._models.py
notification/._views.py
notification/__init__.py
notification/admin.py
notification/atomformat.py
notification/context_processors.py
notification/decorators.py
notification/engine.py
notification/feeds.py
notification/lockfile.py
notification/models.py
notification/urls.py
notification/views.py
notification/management/__init__.py
notification/management/commands/__init__.py
notification/management/commands/emit_notices.py
notification/templates/notification/email_body.txt
notification/templates/notification/email_subject.txt
notification/templates/notification/full.html
notification/templates/notification/full.txt
notification/templates/notification/notice.html
notification/templates/notification/notices.html
notification/templates/notification/short.txt