Metadata-Version: 1.0
Name: django-notification-op
Version: 0.1.6
Summary: User notification management for the Django web framework modified for OpenProximity
Home-page: https://github.com/OpenProximity/django-notification
Author: James Tauber
Author-email: jtauber@jtauber.com
License: UNKNOWN
Platform: UNKNOWN
Classifier: Development Status :: 3 - Alpha
Classifier: Environment :: Web Environment
Classifier: Intended Audience :: Developers
Classifier: License :: OSI Approved :: MIT License
Classifier: Operating System :: OS Independent
Classifier: Programming Language :: Python
Classifier: Framework :: Django
